checkQC/__init__.py
checkQC/app.py
checkQC/config.py
checkQC/exceptions.py
checkQC/qc_data.py
checkQC/qc_engine.py
checkQC/qc_reporter.py
checkQC/run_type_recognizer.py
checkQC/run_type_summarizer.py
checkQC/runfolder_reader.py
checkQC/web_app.py
checkQC/default_config/config.yaml
checkQC/default_config/config_schema.json
checkQC/default_config/logger.yaml
checkQC/handlers/__init__.py
checkQC/handlers/cluster_pf_handler.py
checkQC/handlers/error_rate_handler.py
checkQC/handlers/q30_handler.py
checkQC/handlers/qc_handler.py
checkQC/handlers/qc_handler_factory.py
checkQC/handlers/reads_per_sample_handler.py
checkQC/handlers/undetermined_percentage_handler.py
checkQC/handlers/unidentified_index_handler.py
checkQC/parsers/__init__.py
checkQC/parsers/demux_summary_parser.py
checkQC/parsers/illumina.py
checkQC/parsers/interop_parser.py
checkQC/parsers/parser.py
checkQC/parsers/samplesheet_parser.py
checkQC/parsers/stats_json_parser.py
checkQC/qc_checkers/__init__.py
checkQC/qc_checkers/cluster_pf.py
checkQC/qc_checkers/error_rate.py
checkQC/qc_checkers/q30.py
checkQC/qc_checkers/reads_per_sample.py
checkQC/qc_checkers/undetermined_percentage.py
checkQC/qc_checkers/unidentified_index.py
checkQC/qc_checkers/utils.py
checkQC/views/__init__.py
checkQC/views/basic.py
checkQC/views/illumina.py
checkqc-4.1.0.dist-info/licenses/LICENSE
checkqc-4.1.0.dist-info/METADATA
checkqc-4.1.0.dist-info/WHEEL
checkqc-4.1.0.dist-info/entry_points.txt
checkqc-4.1.0.dist-info/top_level.txt
checkqc-4.1.0.dist-info/RECORD
