Metadata-Version: 2.4
Name: checkQC
Version: 4.1.0
Summary: A simple program to parse Illumina NGS data and check it for quality criteria.
Home-page: https://www.github.com/Molmed/checkQC
Download-URL: https://github.com/Molmed/checkQC/archive/4.1.0.tar.gz
Author: Johan Dahlberg, SNP&SEQ Technology Platform, Uppsala University
Author-email: johan.dahlberg@medsci.uu.se
License: GPLv3
Keywords: bioinformatics,ngs,quality control
Requires-Python: >3.10, <3.11
License-File: LICENSE
Requires-Dist: click
Requires-Dist: PyYAML>=6.0
Requires-Dist: interop>=1.2.4
Requires-Dist: xmltodict
Requires-Dist: tornado
Requires-Dist: sample_sheet
Dynamic: author
Dynamic: author-email
Dynamic: description
Dynamic: download-url
Dynamic: home-page
Dynamic: keywords
Dynamic: license
Dynamic: license-file
Dynamic: requires-dist
Dynamic: requires-python
Dynamic: summary
